pytest_test_this.py
pytest_test_this-0.3.0.dist-info/AUTHORS.rst
pytest_test_this-0.3.0.dist-info/LICENSE
pytest_test_this-0.3.0.dist-info/METADATA
pytest_test_this-0.3.0.dist-info/WHEEL
pytest_test_this-0.3.0.dist-info/entry_points.txt
pytest_test_this-0.3.0.dist-info/top_level.txt
pytest_test_this-0.3.0.dist-info/RECORD
