Metadata-Version: 2.1
Name: pytest-test-this
Version: 0.3.0
Summary: Plugin for py.test to run relevant tests, based on naively checking if a test contains a reference to the symbol you supply
Home-page: https://github.com/boxed/pytest-test-this
Author: Anders Hovmöller
Author-email: boxed@killingar.net
License: BSD
Keywords: pytest,py.test,pycharm
Platform: UNKNOWN
Classifier: Development Status :: 2 - Pre-Alpha
Classifier: Intended Audience :: Developers
Classifier: License :: OSI Approved :: BSD License
Classifier: Natural Language :: English
Classifier: Operating System :: POSIX
Classifier: Operating System :: Microsoft :: Windows
Classifier: Operating System :: MacOS :: MacOS X
Classifier: Topic :: Software Development :: Testing
Classifier: Topic :: Software Development :: Libraries
Classifier: Topic :: Utilities
Classifier: Programming Language :: Python :: 3
Classifier: Programming Language :: Python :: 3.6
Classifier: Programming Language :: Python :: 3.7
Classifier: Programming Language :: Python :: 3.8
Classifier: Framework :: Pytest
Requires-Dist: pytest (>=2.3)
